{":-": 2, "gu": 3, "gs": 2, "gr": 2, "z\u00e1": 1, "ge": 3, "ga": 1, "go": 8, ":0": 1, "gi": 1, "gh": 1, "tz": 1, "\ud83d\udc50": 1, "-m": 1, "tw": 2, "tt": 1, "tu": 1, "tr": 5, "ts": 3, "to": 7, "\ud83d\udc40": 1, "th": 13, "ti": 5, "te": 14, "ta": 5, "\ufe0f\u2764": 2, "g.": 1, "-\"": 1, "-)": 1, "-(": 1, "t.": 4, "t!": 1, "ze": 1, "&a": 1, "t\u00e1": 1, "\udffc\ud83d": 5, "\udc50\ud83c": 1, "\ud83d\udc9b": 1, "\ud83d\udc9a": 1, "\u30c8\u30a2": 1, "va": 2, "\udc9b\ud83d": 1, "ip": 1, "\u0643\u064a": 2, "iu": 1, "\u0648\u0638": 1, "f\u00e9": 1, "me": 13, "ma": 7, "mb": 1, "mm": 3, "mo": 6, "mi": 11, "\"v": 1, "mk": 1, "mu": 1, "s\u00e9": 1, "mp": 2, "ms": 1, "my": 1, "\u30ab\u30d9": 1, "f.": 1, "s.": 1, "s,": 3, "s!": 2, "fr": 1, "ft": 2, "fa": 4, "fe": 2, "ff": 2, "fi": 1, "fl": 2, "fo": 3, "\ud83d\udd95": 6, "m\u00e1": 2, "\u30ab\u30ab": 1, "su": 3, "\u0648\u0627": 1, "sk": 1, "si": 4, "so": 9, "sm": 5, "sl": 2, "sc": 4, "sa": 10, "se": 10, "\ud83c\udfb6": 1, "y.": 2, "lf": 1, "lg": 2, "ld": 3, "le": 7, "lc": 1, "la": 14, "lo": 9, "ll": 11, "lh": 1, "li": 10, "lv": 2, "lt": 1, "lu": 1, "ls": 1, "ly": 5, "\ud83d\ude37": 1, "\ud83d\ude31": 1, "yo": 5, "ya": 1, "\ud83c\udffc": 7, "ye": 3, "\u5ddd\u5e02": 1, "ys": 1, "yt": 1, "yw": 1, "\ud83d\ude13": 1, "l.": 1, "\ud83d\ude04": 1, "\ud83d\ude06": 5, "\ud83d\ude0d": 1, "\u0635\u0627": 1, "em": 5, "el": 12, "\u0638\u0628": 1, "en": 15, "ei": 1, "ej": 1, "ee": 4, "ed": 8, "ea": 4, "ec": 2, "ey": 2, "\ud83c\udf20": 1, "ez": 1, "et": 4, "ew": 1, "ev": 3, "eq": 1, "ep": 2, "es": 15, "er": 20, "rt": 6, "ru": 2, "rs": 2, "\ude06\ud83d": 4, "rd": 6, "re": 16, "rg": 1, "ra": 11, "rn": 1, "ro": 6, "rh": 1, "ri": 3, "rk": 1, "e,": 2, "n\u00e9": 1, "e!": 3, "e?": 1, "\u00f1a": 1, "r.": 1, "\u5c4b\u5ddd": 1, "\u0631\u0648": 1, "\u2764\ufe0f": 5, "\u30c3\u30b0": 1, "\ufe0f\ud83d": 1, "ss": 4, "\u0627\u062f": 1, "\u0627\u062e": 1, "st": 8, "\u0627\u0628": 1, "\u8431\u5cf6": 1, "\u5e02,": 1, "ka": 2, "ke": 1, "kk": 1, "ki": 2, "ks": 1, "\u0627\u0646": 1, "\u0627\u0644": 2, "d-": 2, "\u00e9r": 1, "\u00e9m": 1, "\u064a\u0646": 1, "dn": 2, "do": 21, "dk": 1, "di": 11, "de": 6, "da": 9, "ds": 1, "qu": 9, "\u064a\u0631": 2, "\u064a\u0633": 1, "\u064a\u0629": 1, "\u5927\u962a": 1, "00": 1, "wn": 1, "\u30e9\u30c3": 1, "we": 2, "d\u00ed": 1, "wa": 2, "wo": 4, "ju": 1, "wi": 2, "wh": 3, "jo": 2, "je": 1, "ja": 3, "\u30c9\u30e9": 1, "\u0633\u062c": 1, "ck": 1, "ci": 3, "ch": 5, "co": 9, "i\u00f1": 1, "ca": 10, "ce": 3, "\u0646\u0643": 1, "cr": 2, "\u0646\u064a": 1, "cu": 3, "ct": 1, "pr": 5, "ps": 1, "pp": 1, "pq": 1, "\u0644\u0648": 2, "py": 1, "\u0639\u0645": 1, "pa": 6, "pd": 1, "pe": 4, "po": 1, "pl": 3, "\udd95\ud83c": 6, "\u0644\u0645": 1, "\udf20\ud83d": 1, "p;": 1, "p?": 1, "c\u00ea": 1, "ve": 8, "vi": 4, "is": 11, "ir": 2, "\u062f\u0643": 1, "it": 16, "vo": 3, "ik": 2, "vs": 1, "im": 5, "il": 7, "io": 4, "in": 22, "ia": 5, "ic": 7, "ie": 5, "id": 5, "ig": 1, "\ude13\ud83d": 1, "v.": 2, "\u0637\u0644": 1, "i'": 2, "\u062f\u0627": 1, "\u5cf6\u5e97": 1, "\u00e1l": 1, "\u00e1n": 1, "\u00e1s": 2, "(a": 1, "\u5bdd\u5c4b": 1, "\u0628\u064a": 2, "cc": 1, "\u0628\u0648": 1, "i\u00f3": 1, "((": 2, "\u0628\u0627": 1, "m\u2764": 1, "\ud83d\ude1d": 1, "\u0648\u064a": 1, "a\"": 1, "\u0648\u0646": 1, "6:": 1, "o.": 1, "\u0645\u0627": 1, "\u30b0\u30b9": 1, "o!": 1, "\u0645\u0637": 1, "be": 7, "ba": 7, "bb": 1, "\u0645\u0644": 1, "bo": 5, "bi": 4, "bu": 3, "br": 1, "a.": 2, "by": 5, "oo": 2, "on": 15, "om": 4, "ol": 7, "ok": 2, "oi": 3, "of": 3, "od": 1, "oc": 3, "ob": 2, "oa": 1, "\u0648\u0628": 1, "oy": 1, "ow": 4, "ov": 5, "ou": 18, "ot": 1, "os": 5, "or": 11, "op": 1, "!!": 5, "!\ud83d": 1, "\u30b9\u30c8": 1, "..": 6, ".\"": 1, ".?": 1, "hr": 1, "\u062e\u0644": 1, "hu": 1, "hi": 8, "ho": 6, "hl": 1, "ha": 15, "hd": 1, "he": 4, "\u962a\u5e9c": 1, "ut": 6, "up": 1, "us": 2, "ur": 2, "um": 4, "ul": 3, "un": 5, "ui": 2, "ue": 8, "ud": 1, "uf": 1, "ua": 5, "uc": 2, "ac": 3, "ab": 6, "ad": 11, "ag": 5, "af": 3, "ai": 1, "ah": 1, "\u0644\u0644": 2, "aj": 2, "am": 4, "al": 19, "ao": 1, "an": 22, "ap": 2, "\udffc\u2764": 1, "ar": 13, "au": 1, "at": 13, "av": 4, "ay": 4, "az": 1, "as": 16, "nh": 4, "ni": 4, "nj": 1, "nk": 2, "nl": 1, "nn": 2, "no": 10, "\u062c.": 1, "na": 6, "nc": 1, "nd": 17, "ne": 6, "ng": 9, "ny": 2, "nz": 1, "nq": 1, "nr": 1, "ns": 6, "nt": 6, "a!": 3, "'t": 2, "\u0641\u0644": 1, "\u0641\u064a": 1, "\u30a2\u30ab": 1, "h\u00e3": 1, "'m": 2, "n)": 1, "\u0644\u0628": 2, "\u00edn": 1, "n'": 2, "u\u00e9": 1, "n\ud83d": 1, "\u0644\u0639": 1, "u\u00e1": 1}